funkybob/__init__.py
funkybob/data.py
funkybob-2023.12.0.dist-info/METADATA
funkybob-2023.12.0.dist-info/WHEEL
funkybob-2023.12.0.dist-info/top_level.txt
funkybob-2023.12.0.dist-info/RECORD
