Metadata-Version: 2.1
Name: funkybob
Version: 2023.12.0
Home-page: https://github.com/andreacorbellini/funkybob
Author: Andrea Corbellini
Author-email: corbellini.andrea@gmail.com
License: MIT License
